[
    {
        "titre": "I. lignes abstraites",
        "emplacement" : "poignet",
        "date":"2019",
        "url": "assets/img/01tatt.JPG"
    },
    {
        "titre": "II. Silhouette",
        "emplacement" : "côtes",
        "date":"2019" ,
        "url": "assets/img/02tatt.JPG"
    },
    {
        "titre": "III. Fauteil",
        "emplacement" : "haut du bras",
        "date":"2019" ,
        "url": "assets/img/03tatt.JPG"
    },
    {
        "titre": "IV. Dance w/ me",
        "emplacement" : "mollet",
        "date":"2018" ,
        "url": "assets/img/04tatt.JPG"
    },
    {
        "titre": "V. Dance w/ me 2",
        "emplacement" : "suisse",
        "date":"2019" ,
        "url": "assets/img/05tatt.JPG"
    },
    {
        "titre": "VI. Sphynx",
        "emplacement" : "pectoral",
        "date":"2019",
        "url": "assets/img/06tatt.JPG"
    },
    {
        "titre": "VII. Audrey masquée",
        "emplacement" : "poignet",
        "date":"2019" ,
        "url": "assets/img/07tatt.JPG"
    },
    {
        "titre": "VIII. Yeux en bocal",
        "emplacement" : "arrière cuisse",
        "date":"2019" ,
        "url": "assets/img/08tatt.JPG"
    },
    {
        "titre": "IX. Cage à oiseaux",
        "emplacement" : "poignet",
        "date":"2019" ,
        "url": "assets/img/09tatt.JPG"
    },
    {
        "titre": "X. Siblings",
        "emplacement" : "haut du bras",
        "date":"2019" ,
        "url": "assets/img/10tatt.JPG"
    }
]